cstream/__init__.py
cstream/constants.py
cstream/cstream.py
cstream-1.0.4.dist-info/METADATA
cstream-1.0.4.dist-info/WHEEL
cstream-1.0.4.dist-info/top_level.txt
cstream-1.0.4.dist-info/RECORD
