Metadata-Version: 2.1
Name: cstream
Version: 1.0.4
Summary: C++ Style Colorful output stream for Python with debug level capabilities.
Home-page: UNKNOWN
Author: Pedro Maciel Xavier
Author-email: pedromxavier@poli.ufrj.br
License: UNKNOWN
Platform: UNKNOWN
Classifier: Programming Language :: Python :: 3
Requires-Python: <4,>=3.7
Requires-Dist: colorama
